{
  "WorldString: Actionable World Representation": {
    "created_date": "2026-06-20 17:11:25",
    "priority": "high",
    "notes": "Focus on understanding the neural architecture for physical world modeling",
    "todos": [
      {
        "task": "Study how it generalizes FK, LBS, and soft object Jacobians",
        "completed": false,
        "added_date": "2026-06-20 17:11:33"
      },
      {
        "task": "Understand the real-world data acquisition pipeline",
        "completed": false,
        "added_date": "2026-06-20 17:11:33"
      },
      {
        "task": "Understand the WorldString architecture and transformer-based design",
        "completed": false,
        "added_date": "2026-06-20 17:11:33"
      },
      {
        "task": "Review experimental results on articulated, skinning, and soft objects",
        "completed": false,
        "added_date": "2026-06-20 17:11:33"
      },
      {
        "task": "Read abstract and introduction - understand the problem statement",
        "completed": true,
        "added_date": "2026-06-20 17:11:33",
        "completed_date": "2026-06-20 17:11:46"
      }
    ]
  }
}